terrapin_orm/__init__.py
terrapin_orm/fields/__init__.py
terrapin_orm/fields/array.py
terrapin_orm/fields/base.py
terrapin_orm/fields/binary.py
terrapin_orm/fields/boolean.py
terrapin_orm/fields/character.py
terrapin_orm/fields/datetime.py
terrapin_orm/fields/jsonb.py
terrapin_orm/fields/numeric.py
terrapin_orm/fields/uuid.py
terrapin_orm/table.py
terrapin_orm-0.0.2.dist-info/LICENSE
terrapin_orm-0.0.2.dist-info/METADATA
terrapin_orm-0.0.2.dist-info/WHEEL
terrapin_orm-0.0.2.dist-info/RECORD
